neops_worker_sdk/__init__.py
neops_worker_sdk/cli/__init__.py
neops_worker_sdk/cli/neops_worker.py
neops_worker_sdk/function_block/__init__.py
neops_worker_sdk/function_block/function_block.py
neops_worker_sdk/registry/__init__.py
neops_worker_sdk-0.1.0.dist-info/METADATA
neops_worker_sdk-0.1.0.dist-info/WHEEL
neops_worker_sdk-0.1.0.dist-info/entry_points.txt
neops_worker_sdk-0.1.0.dist-info/RECORD
