Metadata-Version: 2.1
Name: neops_worker_sdk
Version: 0.1.0
Summary: 
Author: zebbra AG
Requires-Python: >=3.12,<4.0
Classifier: Programming Language :: Python :: 3
Classifier: Programming Language :: Python :: 3.12
Requires-Dist: neops_graphql (>=1.7.31,<2.0.0)
